zinemachine/__init__.py
zinemachine/__main__.py
zinemachine/bluetoothprintermanager.py
zinemachine/button.py
zinemachine/consoleprinter.py
zinemachine/consoleprintermanager.py
zinemachine/inputmanager.py
zinemachine/keyboardbutton.py
zinemachine/markup.py
zinemachine/profile.py
zinemachine/zine.py
zinemachine/zinemachine.py
zinemachine/zinevalidator.py
zinemachine-1.0.0.dist-info/LICENSE
zinemachine-1.0.0.dist-info/METADATA
zinemachine-1.0.0.dist-info/WHEEL
zinemachine-1.0.0.dist-info/top_level.txt
zinemachine-1.0.0.dist-info/RECORD
