Metadata-Version: 2.1
Name: zinemachine
Version: 1.0.0
Summary: print zines from a receipt printer using raspberry pi
Author-email: Elliot Hatch <elliot.hatch@gmail.com>
License: GNU GENERAL PUBLIC LICENSE
Project-URL: Homepage, https://elliot.zone/zinemachine
Project-URL: Repository, https://github.com/elliothatch/zine-machine.git
Project-URL: Changelog, https://github.com/elliothatch/zine-machine/blob/master/CHANGES.md
Keywords: zine,printer,receipt printer,POS printer,escpos
Classifier: Development Status :: 4 - Beta
Classifier: License :: OSI Approved :: GNU General Public License v2 (GPLv2)
Classifier: Programming Language :: Python :: 3 :: Only
Classifier: Programming Language :: Python :: 3.7
Classifier: Programming Language :: Python :: 3.8
Classifier: Programming Language :: Python :: 3.9
Classifier: Programming Language :: Python :: 3.10
Classifier: Programming Language :: Python :: 3.11
Requires-Python: >=3.7
License-File: LICENSE
Requires-Dist: python-escpos ==3.0a8
Requires-Dist: RPi.GPIO
Requires-Dist: Pillow >=9.1.0
